aesthetic_predictor_v2_5/__init__.py
aesthetic_predictor_v2_5/siglip_v2_5.py
aesthetic_predictor_v2_5-2024.12.18.1.dist-info/METADATA
aesthetic_predictor_v2_5-2024.12.18.1.dist-info/WHEEL
aesthetic_predictor_v2_5-2024.12.18.1.dist-info/licenses/LICENSE
aesthetic_predictor_v2_5-2024.12.18.1.dist-info/RECORD
