Metadata-Version: 2.3
Name: aesthetic-predictor-v2-5
Version: 2024.12.18.1
Summary: Aesthetic predictor v2.5
Author-email: Verb <discus0434@gmail.com>
License:                     GNU AFFERO GENERAL PUBLIC LICENSE
License-File: LICENSE
Classifier: Intended Audience :: Developers
Classifier: License :: OSI Approved :: GNU Affero General Public License v3
Classifier: Programming Language :: Python :: 3
Classifier: Programming Language :: Python :: 3.9
Classifier: Programming Language :: Python :: 3.10
Classifier: Programming Language :: Python :: 3.11
Classifier: Programming Language :: Python :: 3.12
Classifier: Programming Language :: Python :: 3.13
Classifier: Topic :: Scientific/Engineering :: Artificial Intelligence
Requires-Dist: accelerate>=0.30
Requires-Dist: numpy
Requires-Dist: torch>=2.2
Requires-Dist: torchvision>=0.17
Requires-Dist: transformers>=4.40
Provides-Extra: dev
Requires-Dist: datasets; extra == 'dev'
Requires-Dist: datasets>=2.19.0; extra == 'dev'
Requires-Dist: deepspeed>=0.14.2; extra == 'dev'
Requires-Dist: gradio>=4.31; extra == 'dev'
Requires-Dist: mypy; extra == 'dev'
Requires-Dist: pytest; extra == 'dev'
Requires-Dist: ruff; extra == 'dev'
Requires-Dist: simple-aesthetics-predictor>=0.1.2; extra == 'dev'
Requires-Dist: sqlalchemy>=2.0.29; extra == 'dev'
Requires-Dist: timm>=0.9.16; extra == 'dev'
